pyrotest/__init__.py
pyrotest/pyrotest.py
pyrotest/core/base.py
pyrotest/core/base_globals.py
pyrotest/infra/esxi/__init__.py
pyrotest/infra/esxi/esxi_helper.py
pyrotest/logger/__init__.py
pyrotest/logger/logger.py
pyrotest/scale/__init__.py
pyrotest/scale/conftest.py
pyrotest/scale/flexiclient.py
pyrotest/scale/vpnclient.py
pyrotest/tools/__init__.py
pyrotest/tools/kvm_tool.py
pyrotest/utils/tcms/kiwi_tcms.py
pyrotest-0.0.2.dist-info/LICENSE
pyrotest-0.0.2.dist-info/METADATA
pyrotest-0.0.2.dist-info/WHEEL
pyrotest-0.0.2.dist-info/top_level.txt
pyrotest-0.0.2.dist-info/RECORD
