Metadata-Version: 2.1
Name: pyrotest
Version: 0.0.2
Summary: pyroTest package 
Author-email: Pugazhenthi Thirukkami <pugalcse@gmail.com>
Project-URL: Homepage, https://gitlab.com/pugazh-network-consulting/topology-builder
Project-URL: Issues, https://gitlab.com/pugazh-network-consulting/topology-builder/-/issues
Classifier: Programming Language :: Python :: 3
Classifier: License :: OSI Approved :: MIT License
Classifier: Operating System :: OS Independent
Requires-Python: >=3.8
License-File: LICENSE
